Metadata-Version: 2.4
Name: mroudai-django-notifications
Version: 0.1.0
Summary: Event-driven transactional notifications for Django booking and SaaS workflows.
Author: Open Source Contributors
License: MIT License
Project-URL: Homepage, https://example.com
Project-URL: Source, https://example.com
Classifier: Framework :: Django
Classifier: Framework :: Django :: 4.2
Classifier: Framework :: Django :: 5.0
Classifier: License :: OSI Approved :: MIT License
Classifier: Programming Language :: Python :: 3
Classifier: Programming Language :: Python :: 3 :: Only
Classifier: Programming Language :: Python :: 3.10
Classifier: Programming Language :: Python :: 3.11
Classifier: Programming Language :: Python :: 3.12
Requires-Python: >=3.10
License-File: LICENSE
Requires-Dist: Django>=4.2
Dynamic: license-file
